{
  "schema": "threenative.scene",
  "version": "0.1.0",
  "id": "arena",
  "kind": "level",
  "entities": [
    {
      "id": "visual.provenance",
      "prefab": "prefab.sign",
      "transform": { "position": [-5.6, 0.42, 4.55], "scale": [1.25, 0.26, 0.08] },
      "components": {
        "VisualProvenance": {
          "catalogSearches": "boats/nautical/ships direct GLB searches returned TN_ASSET_SOURCE_NO_MATCH",
          "fallback": "custom-authored low-poly harbor kit using structured-source primitive compositions",
          "surfaces": "player-hero tugboat, obstacle-enemy hazard whirlpools, reward-interactable distress buoys, world-environment harbor, ui-hud, audio-feedback"
        }
      }
    },
    {
      "id": "camera.main",
      "transform": { "position": [0, 9.6, 8.8], "rotation": [-0.88, 0, 0] },
      "components": { "camera": { "mode": "perspective", "fovY": 48, "near": 0.05, "far": 90 } }
    },
    { "id": "light.ambient", "components": { "Light": { "kind": "ambient", "color": "#9fc9e8", "intensity": 0.62 } } },
    { "id": "light.moon", "transform": { "position": [-4.8, 7.2, 5.4], "rotation": [-0.85, -0.46, 0] }, "components": { "Light": { "kind": "directional", "color": "#dbeeff", "intensity": 1.24 } } },
    { "id": "light.beacon", "transform": { "position": [3.35, 2.85, -3.65] }, "components": { "Light": { "kind": "point", "color": "#ffd86a", "intensity": 5.8, "range": 9.8 } } },
    { "id": "light.buoy", "transform": { "position": [-1.5, 0.85, 2.15] }, "components": { "Light": { "kind": "point", "color": "#ff9860", "intensity": 2.4, "range": 6 } } },

    { "id": "harbor.water", "prefab": "prefab.water", "transform": { "position": [0, -0.08, 0], "rotation": [-1.570796, 0, 0], "scale": [11.5, 10.4, 1] } },
    { "id": "harbor.channel", "prefab": "prefab.channel", "transform": { "position": [0, -0.055, 0.15], "rotation": [-1.570796, 0, 0], "scale": [5.7, 8.5, 1] } },
    { "id": "foam.lane.01", "prefab": "prefab.foam-strip", "transform": { "position": [-2.9, 0.01, 0.2], "scale": [0.06, 0.02, 7.6] } },
    { "id": "foam.lane.02", "prefab": "prefab.foam-strip", "transform": { "position": [2.9, 0.01, 0.2], "scale": [0.06, 0.02, 7.6] } },
    { "id": "wave.channel.01", "prefab": "prefab.wave-cool", "transform": { "position": [-1.95, 0.018, 3.12], "rotation": [-1.570796, 0, 0.24], "scale": [1.05, 0.045, 1] } },
    { "id": "wave.channel.02", "prefab": "prefab.wave-bright", "transform": { "position": [1.55, 0.019, 2.35], "rotation": [-1.570796, 0, -0.22], "scale": [1.18, 0.045, 1] } },
    { "id": "wave.channel.03", "prefab": "prefab.wave-cool", "transform": { "position": [-1.42, 0.02, 0.9], "rotation": [-1.570796, 0, -0.18], "scale": [1.25, 0.045, 1] } },
    { "id": "wave.channel.04", "prefab": "prefab.wave-bright", "transform": { "position": [1.8, 0.021, -0.45], "rotation": [-1.570796, 0, 0.2], "scale": [1.08, 0.045, 1] } },
    { "id": "wave.channel.05", "prefab": "prefab.wave-cool", "transform": { "position": [-1.05, 0.022, -2.35], "rotation": [-1.570796, 0, 0.28], "scale": [1.16, 0.045, 1] } },
    { "id": "wave.outer.left.01", "prefab": "prefab.wave-dark", "transform": { "position": [-4.05, 0.018, 2.0], "rotation": [-1.570796, 0, -0.18], "scale": [1.0, 0.04, 1] } },
    { "id": "wave.outer.right.01", "prefab": "prefab.wave-dark", "transform": { "position": [4.1, 0.018, 1.1], "rotation": [-1.570796, 0, 0.18], "scale": [1.0, 0.04, 1] } },
    { "id": "storm.flash.left", "prefab": "prefab.storm-flash", "transform": { "position": [-4.55, 0.025, -3.45], "rotation": [-1.570796, 0, 0.45], "scale": [0.52, 0.06, 1] } },
    { "id": "storm.flash.right", "prefab": "prefab.storm-flash", "transform": { "position": [4.35, 0.025, -2.65], "rotation": [-1.570796, 0, -0.36], "scale": [0.46, 0.06, 1] } },
    { "id": "breakwater.left", "prefab": "prefab.breakwater", "transform": { "position": [-4.85, 0.24, 0.4], "scale": [0.5, 0.42, 8.8] } },
    { "id": "breakwater.right", "prefab": "prefab.breakwater", "transform": { "position": [4.85, 0.24, 0.4], "scale": [0.5, 0.42, 8.8] } },
    { "id": "breakwater.back", "prefab": "prefab.breakwater", "transform": { "position": [0, 0.24, 4.85], "scale": [9.25, 0.42, 0.44] } },

    { "id": "dock.deck", "prefab": "prefab.dock", "transform": { "position": [3.25, 0.18, -3.48], "scale": [2.4, 0.18, 1.15] }, "components": { "DockGoal": { "radius": 1.1 } } },
    { "id": "dock.plank.01", "prefab": "prefab.dock-plank", "transform": { "position": [2.55, 0.34, -3.48], "scale": [0.08, 0.055, 1.12] } },
    { "id": "dock.plank.02", "prefab": "prefab.dock-plank-dark", "transform": { "position": [3.18, 0.35, -3.48], "scale": [0.08, 0.055, 1.12] } },
    { "id": "dock.plank.03", "prefab": "prefab.dock-plank", "transform": { "position": [3.8, 0.34, -3.48], "scale": [0.08, 0.055, 1.12] } },
    { "id": "dock.rope.front", "prefab": "prefab.rope", "transform": { "position": [3.25, 0.62, -2.88], "scale": [2.05, 0.045, 0.06] } },
    { "id": "dock.rope.back", "prefab": "prefab.rope", "transform": { "position": [3.25, 0.62, -4.08], "scale": [2.05, 0.045, 0.06] } },
    { "id": "dock.post.01", "prefab": "prefab.post", "transform": { "position": [2.1, 0.42, -2.92], "scale": [0.16, 0.82, 0.16] } },
    { "id": "dock.post.02", "prefab": "prefab.post", "transform": { "position": [4.4, 0.42, -2.92], "scale": [0.16, 0.82, 0.16] } },
    { "id": "dock.post.03", "prefab": "prefab.post", "transform": { "position": [2.1, 0.42, -4.04], "scale": [0.16, 0.82, 0.16] } },
    { "id": "dock.post.04", "prefab": "prefab.post", "transform": { "position": [4.4, 0.42, -4.04], "scale": [0.16, 0.82, 0.16] } },
    { "id": "lighthouse.base", "prefab": "prefab.lighthouse", "transform": { "position": [3.35, 1.0, -4.32], "scale": [0.52, 1.65, 0.52] } },
    { "id": "lighthouse.stripe.01", "prefab": "prefab.lighthouse-stripe", "transform": { "position": [3.35, 1.12, -4.31], "scale": [0.56, 0.14, 0.56] } },
    { "id": "lighthouse.stripe.02", "prefab": "prefab.lighthouse-stripe", "transform": { "position": [3.35, 1.62, -4.31], "scale": [0.56, 0.14, 0.56] } },
    { "id": "lighthouse.beacon", "prefab": "prefab.beacon", "transform": { "position": [3.35, 2.78, -4.32], "scale": [0.42, 0.24, 0.42] }, "components": { "BeaconPulse": { "base": [3.35, 2.78, -4.32], "phase": 0 } } },
    { "id": "lighthouse.ray.left", "prefab": "prefab.beacon-ray", "transform": { "position": [2.88, 2.82, -4.02], "rotation": [0.14, 0.5, -0.24], "scale": [0.07, 0.04, 1.05] } },
    { "id": "lighthouse.ray.right", "prefab": "prefab.beacon-ray", "transform": { "position": [3.82, 2.82, -4.02], "rotation": [0.14, -0.5, 0.24], "scale": [0.07, 0.04, 1.05] } },
    { "id": "lighthouse.roof", "prefab": "prefab.roof", "transform": { "position": [3.35, 3.1, -4.32], "scale": [0.55, 0.38, 0.55] } },

    { "id": "player", "prefab": "prefab.tug-hull", "transform": { "position": [0, 0.2, 3.55], "rotation": [0, 3.141593, 0], "scale": [0.72, 0.25, 1.02] }, "components": { "Tugboat": { "speed": 3.0, "carried": 0, "delivered": 0 } } },
    { "id": "player.deck", "prefab": "prefab.tug-deck", "transform": { "position": [0, 0.44, 3.72], "scale": [0.52, 0.16, 0.58] } },
    { "id": "player.cabin", "prefab": "prefab.tug-cabin", "transform": { "position": [0, 0.64, 3.48], "scale": [0.34, 0.3, 0.36] } },
    { "id": "player.trim.left", "prefab": "prefab.tug-trim", "transform": { "position": [-0.42, 0.34, 3.55], "scale": [0.05, 0.08, 0.9] } },
    { "id": "player.trim.right", "prefab": "prefab.tug-trim", "transform": { "position": [0.42, 0.34, 3.55], "scale": [0.05, 0.08, 0.9] } },
    { "id": "player.stack", "prefab": "prefab.stack", "transform": { "position": [0.28, 0.78, 3.62], "scale": [0.08, 0.34, 0.08] } },
    { "id": "player.bow.light", "prefab": "prefab.marker", "transform": { "position": [0, 0.5, 2.95], "scale": [0.1, 0.1, 0.1] } },
    { "id": "player.wake.left", "prefab": "prefab.tug-wake", "transform": { "position": [-0.38, 0.02, 4.08], "rotation": [-1.570796, 0, 0.12], "scale": [0.22, 0.72, 1] } },
    { "id": "player.wake.right", "prefab": "prefab.tug-wake", "transform": { "position": [0.38, 0.02, 4.08], "rotation": [-1.570796, 0, -0.12], "scale": [0.22, 0.72, 1] } },

    { "id": "buoy.01", "prefab": "prefab.buoy", "transform": { "position": [-1.85, 0.36, 2.12], "scale": [0.22, 0.34, 0.22] }, "components": { "DistressBuoy": { "collected": false, "phase": 0.2 } } },
    { "id": "buoy.01.halo", "prefab": "prefab.buoy-halo", "transform": { "position": [-1.85, 0.065, 2.12], "scale": [0.68, 0.035, 0.68] } },
    { "id": "buoy.01.light", "prefab": "prefab.buoy-light", "transform": { "position": [-1.85, 0.76, 2.12], "scale": [0.15, 0.15, 0.15] } },
    { "id": "buoy.02", "prefab": "prefab.buoy", "transform": { "position": [1.72, 0.36, 1.32], "scale": [0.22, 0.34, 0.22] }, "components": { "DistressBuoy": { "collected": false, "phase": 0.9 } } },
    { "id": "buoy.02.halo", "prefab": "prefab.buoy-halo", "transform": { "position": [1.72, 0.065, 1.32], "scale": [0.68, 0.035, 0.68] } },
    { "id": "buoy.02.light", "prefab": "prefab.buoy-light", "transform": { "position": [1.72, 0.76, 1.32], "scale": [0.15, 0.15, 0.15] } },
    { "id": "buoy.03", "prefab": "prefab.buoy", "transform": { "position": [-1.35, 0.36, -0.32], "scale": [0.22, 0.34, 0.22] }, "components": { "DistressBuoy": { "collected": false, "phase": 1.8 } } },
    { "id": "buoy.03.halo", "prefab": "prefab.buoy-halo", "transform": { "position": [-1.35, 0.065, -0.32], "scale": [0.68, 0.035, 0.68] } },
    { "id": "buoy.03.light", "prefab": "prefab.buoy-light", "transform": { "position": [-1.35, 0.76, -0.32], "scale": [0.15, 0.15, 0.15] } },
    { "id": "buoy.04", "prefab": "prefab.buoy", "transform": { "position": [2.15, 0.36, -1.52], "scale": [0.22, 0.34, 0.22] }, "components": { "DistressBuoy": { "collected": false, "phase": 2.7 } } },
    { "id": "buoy.04.halo", "prefab": "prefab.buoy-halo", "transform": { "position": [2.15, 0.065, -1.52], "scale": [0.68, 0.035, 0.68] } },
    { "id": "buoy.04.light", "prefab": "prefab.buoy-light", "transform": { "position": [2.15, 0.76, -1.52], "scale": [0.15, 0.15, 0.15] } },
    { "id": "buoy.05", "prefab": "prefab.buoy", "transform": { "position": [-2.05, 0.36, -2.62], "scale": [0.22, 0.34, 0.22] }, "components": { "DistressBuoy": { "collected": false, "phase": 3.5 } } },
    { "id": "buoy.05.halo", "prefab": "prefab.buoy-halo", "transform": { "position": [-2.05, 0.065, -2.62], "scale": [0.68, 0.035, 0.68] } },
    { "id": "buoy.05.light", "prefab": "prefab.buoy-light", "transform": { "position": [-2.05, 0.76, -2.62], "scale": [0.15, 0.15, 0.15] } },

    { "id": "whirlpool.01", "prefab": "prefab.whirlpool", "transform": { "position": [-0.5, 0.04, 0.78], "scale": [0.72, 0.06, 0.72] }, "components": { "Whirlpool": { "origin": [-0.5, 0.04, 0.78], "axis": "x", "radius": 1.0, "phase": 0.4 } } },
    { "id": "whirlpool.01.foam", "prefab": "prefab.foam-ring", "transform": { "position": [-0.5, 0.08, 0.78], "scale": [0.96, 0.035, 0.96] }, "components": { "WhirlpoolWake": { "target": "whirlpool.01", "offset": [0, 0.04, 0] } } },
    { "id": "whirlpool.02", "prefab": "prefab.whirlpool", "transform": { "position": [0.86, 0.04, -1.18], "scale": [0.68, 0.06, 0.68] }, "components": { "Whirlpool": { "origin": [0.86, 0.04, -1.18], "axis": "z", "radius": 0.95, "phase": 1.8 } } },
    { "id": "whirlpool.02.foam", "prefab": "prefab.foam-ring", "transform": { "position": [0.86, 0.08, -1.18], "scale": [0.9, 0.035, 0.9] }, "components": { "WhirlpoolWake": { "target": "whirlpool.02", "offset": [0, 0.04, 0] } } },

    { "id": "rock.01", "prefab": "prefab.rock", "transform": { "position": [-3.8, 0.24, 2.7], "scale": [0.78, 0.42, 0.6] } },
    { "id": "rock.01.highlight", "prefab": "prefab.rock-highlight", "transform": { "position": [-3.72, 0.48, 2.56], "scale": [0.32, 0.04, 0.22] } },
    { "id": "rock.02", "prefab": "prefab.rock", "transform": { "position": [-3.65, 0.24, -2.2], "scale": [0.66, 0.38, 0.78] } },
    { "id": "rock.02.highlight", "prefab": "prefab.rock-highlight", "transform": { "position": [-3.52, 0.46, -2.34], "scale": [0.28, 0.04, 0.25] } },
    { "id": "rock.03", "prefab": "prefab.rock", "transform": { "position": [3.82, 0.24, 2.45], "scale": [0.78, 0.36, 0.58] } },
    { "id": "rock.03.highlight", "prefab": "prefab.rock-highlight", "transform": { "position": [3.72, 0.45, 2.32], "scale": [0.32, 0.04, 0.2] } },
    { "id": "rock.04", "prefab": "prefab.rock", "transform": { "position": [4.05, 0.24, -0.92], "scale": [0.56, 0.32, 0.52] } },
    { "id": "net.rack", "prefab": "prefab.dock", "transform": { "position": [-3.6, 0.45, 3.78], "scale": [1.15, 0.12, 0.42] } },
    { "id": "marker.start", "prefab": "prefab.marker", "transform": { "position": [0, 0.16, 3.2], "scale": [0.22, 0.08, 0.22] } }
  ],
  "prefabs": [
    { "id": "prefab.water", "primitive": "plane", "color": "#183a4a" },
    { "id": "prefab.channel", "primitive": "plane", "color": "#24586c" },
    { "id": "prefab.foam-strip", "primitive": "box", "color": "#b8f4ff" },
    { "id": "prefab.wave-cool", "primitive": "plane", "color": "#66b7c8" },
    { "id": "prefab.wave-bright", "primitive": "plane", "color": "#d9fbff" },
    { "id": "prefab.wave-dark", "primitive": "plane", "color": "#0d2632" },
    { "id": "prefab.storm-flash", "primitive": "plane", "color": "#ffe766" },
    { "id": "prefab.breakwater", "primitive": "box", "color": "#25313a" },
    { "id": "prefab.dock", "primitive": "box", "color": "#7a5639" },
    { "id": "prefab.dock-plank", "primitive": "box", "color": "#a06f45" },
    { "id": "prefab.dock-plank-dark", "primitive": "box", "color": "#5d3d28" },
    { "id": "prefab.rope", "primitive": "box", "color": "#d6aa62" },
    { "id": "prefab.post", "primitive": "cylinder", "color": "#62442e" },
    { "id": "prefab.lighthouse", "primitive": "cylinder", "color": "#fff0d1" },
    { "id": "prefab.lighthouse-stripe", "primitive": "cylinder", "color": "#d64545" },
    { "id": "prefab.beacon", "primitive": "sphere", "color": "#ffd86a" },
    { "id": "prefab.beacon-ray", "primitive": "box", "color": "#ffe766" },
    { "id": "prefab.roof", "primitive": "cone", "color": "#26313b" },
    { "id": "prefab.tug-hull", "primitive": "box", "color": "#c64638" },
    { "id": "prefab.tug-deck", "primitive": "box", "color": "#f0d19a" },
    { "id": "prefab.tug-cabin", "primitive": "box", "color": "#e8f4ff" },
    { "id": "prefab.tug-trim", "primitive": "box", "color": "#ffe766" },
    { "id": "prefab.tug-wake", "primitive": "plane", "color": "#b8f4ff" },
    { "id": "prefab.stack", "primitive": "cylinder", "color": "#25313a" },
    { "id": "prefab.marker", "primitive": "sphere", "color": "#55e4c8" },
    { "id": "prefab.buoy", "primitive": "cylinder", "color": "#ff6f31" },
    { "id": "prefab.buoy-halo", "primitive": "cylinder", "color": "#ffd86a" },
    { "id": "prefab.buoy-light", "primitive": "sphere", "color": "#ffe766" },
    { "id": "prefab.whirlpool", "primitive": "cylinder", "color": "#347f9a" },
    { "id": "prefab.foam-ring", "primitive": "cylinder", "color": "#b8f4ff" },
    { "id": "prefab.rock", "primitive": "sphere", "color": "#56626b" },
    { "id": "prefab.rock-highlight", "primitive": "box", "color": "#8ca0ad" },
    { "id": "prefab.sign", "primitive": "box", "color": "#1b2730" }
  ],
  "resources": [
    {
      "id": "GameState",
      "value": {
        "phase": "playing",
        "carried": 0,
        "delivered": 0,
        "timer": 80,
        "buoyText": "Buoys 0/5",
        "timerText": "Storm 80",
        "status": "Collect glowing buoys, then dock at the lighthouse"
      }
    }
  ]
}
