{
  "schema": "threenative.scene",
  "version": "0.1.0",
  "id": "chess",
  "entities": [
    {
      "id": "piece.white.pawn.a2",
      "prefab": "prefab.white.pawn",
      "transform": {
        "position": [
          -3.6260000000000003,
          0.07,
          2.59
        ],
        "scale": [
          10.5,
          10.5,
          10.5
        ]
      },
      "components": {
        "ChessPiece": {
          "color": "white",
          "kind": "pawn",
          "initialKind": "pawn",
          "file": 0,
          "rank": 1,
          "initialFile": 0,
          "initialRank": 1,
          "moved": false,
          "alive": true
        }
      }
    },
    {
      "id": "piece.white.rook.a1",
      "prefab": "prefab.white.rook",
      "transform": {
        "position": [
          -3.6260000000000003,
          0.07,
          3.6260000000000003
        ],
        "scale": [
          10.5,
          10.5,
          10.5
        ]
      },
      "components": {
        "ChessPiece": {
          "color": "white",
          "kind": "rook",
          "initialKind": "rook",
          "file": 0,
          "rank": 0,
          "initialFile": 0,
          "initialRank": 0,
          "moved": false,
          "alive": true
        }
      }
    },
    {
      "id": "piece.white.pawn.b2",
      "prefab": "prefab.white.pawn",
      "transform": {
        "position": [
          -2.59,
          0.07,
          2.59
        ],
        "scale": [
          10.5,
          10.5,
          10.5
        ]
      },
      "components": {
        "ChessPiece": {
          "color": "white",
          "kind": "pawn",
          "initialKind": "pawn",
          "file": 1,
          "rank": 1,
          "initialFile": 1,
          "initialRank": 1,
          "moved": false,
          "alive": true
        }
      }
    },
    {
      "id": "piece.white.knight.b1",
      "prefab": "prefab.white.knight",
      "transform": {
        "position": [
          -2.59,
          0.07,
          3.6260000000000003
        ],
        "scale": [
          10.5,
          10.5,
          10.5
        ]
      },
      "components": {
        "ChessPiece": {
          "color": "white",
          "kind": "knight",
          "initialKind": "knight",
          "file": 1,
          "rank": 0,
          "initialFile": 1,
          "initialRank": 0,
          "moved": false,
          "alive": true
        }
      }
    },
    {
      "id": "piece.white.pawn.c2",
      "prefab": "prefab.white.pawn",
      "transform": {
        "position": [
          -1.554,
          0.07,
          2.59
        ],
        "scale": [
          10.5,
          10.5,
          10.5
        ]
      },
      "components": {
        "ChessPiece": {
          "color": "white",
          "kind": "pawn",
          "initialKind": "pawn",
          "file": 2,
          "rank": 1,
          "initialFile": 2,
          "initialRank": 1,
          "moved": false,
          "alive": true
        }
      }
    },
    {
      "id": "piece.white.bishop.c1",
      "prefab": "prefab.white.bishop",
      "transform": {
        "position": [
          -1.554,
          0.07,
          3.6260000000000003
        ],
        "scale": [
          10.5,
          10.5,
          10.5
        ]
      },
      "components": {
        "ChessPiece": {
          "color": "white",
          "kind": "bishop",
          "initialKind": "bishop",
          "file": 2,
          "rank": 0,
          "initialFile": 2,
          "initialRank": 0,
          "moved": false,
          "alive": true
        }
      }
    },
    {
      "id": "piece.white.pawn.d2",
      "prefab": "prefab.white.pawn",
      "transform": {
        "position": [
          -0.518,
          0.07,
          2.59
        ],
        "scale": [
          10.5,
          10.5,
          10.5
        ]
      },
      "components": {
        "ChessPiece": {
          "color": "white",
          "kind": "pawn",
          "initialKind": "pawn",
          "file": 3,
          "rank": 1,
          "initialFile": 3,
          "initialRank": 1,
          "moved": false,
          "alive": true
        }
      }
    },
    {
      "id": "piece.white.queen.d1",
      "prefab": "prefab.white.queen",
      "transform": {
        "position": [
          -0.518,
          0.07,
          3.6260000000000003
        ],
        "scale": [
          10.5,
          10.5,
          10.5
        ]
      },
      "components": {
        "ChessPiece": {
          "color": "white",
          "kind": "queen",
          "initialKind": "queen",
          "file": 3,
          "rank": 0,
          "initialFile": 3,
          "initialRank": 0,
          "moved": false,
          "alive": true
        }
      }
    },
    {
      "id": "piece.white.pawn.e2",
      "prefab": "prefab.white.pawn",
      "transform": {
        "position": [
          0.518,
          0.07,
          2.59
        ],
        "scale": [
          10.5,
          10.5,
          10.5
        ]
      },
      "components": {
        "ChessPiece": {
          "color": "white",
          "kind": "pawn",
          "initialKind": "pawn",
          "file": 4,
          "rank": 1,
          "initialFile": 4,
          "initialRank": 1,
          "moved": false,
          "alive": true
        }
      }
    },
    {
      "id": "piece.white.king.e1",
      "prefab": "prefab.white.king",
      "transform": {
        "position": [
          0.518,
          0.07,
          3.6260000000000003
        ],
        "scale": [
          10.5,
          10.5,
          10.5
        ]
      },
      "components": {
        "ChessPiece": {
          "color": "white",
          "kind": "king",
          "initialKind": "king",
          "file": 4,
          "rank": 0,
          "initialFile": 4,
          "initialRank": 0,
          "moved": false,
          "alive": true
        }
      }
    },
    {
      "id": "piece.white.pawn.f2",
      "prefab": "prefab.white.pawn",
      "transform": {
        "position": [
          1.554,
          0.07,
          2.59
        ],
        "scale": [
          10.5,
          10.5,
          10.5
        ]
      },
      "components": {
        "ChessPiece": {
          "color": "white",
          "kind": "pawn",
          "initialKind": "pawn",
          "file": 5,
          "rank": 1,
          "initialFile": 5,
          "initialRank": 1,
          "moved": false,
          "alive": true
        }
      }
    },
    {
      "id": "piece.white.bishop.f1",
      "prefab": "prefab.white.bishop",
      "transform": {
        "position": [
          1.554,
          0.07,
          3.6260000000000003
        ],
        "scale": [
          10.5,
          10.5,
          10.5
        ]
      },
      "components": {
        "ChessPiece": {
          "color": "white",
          "kind": "bishop",
          "initialKind": "bishop",
          "file": 5,
          "rank": 0,
          "initialFile": 5,
          "initialRank": 0,
          "moved": false,
          "alive": true
        }
      }
    },
    {
      "id": "piece.white.pawn.g2",
      "prefab": "prefab.white.pawn",
      "transform": {
        "position": [
          2.59,
          0.07,
          2.59
        ],
        "scale": [
          10.5,
          10.5,
          10.5
        ]
      },
      "components": {
        "ChessPiece": {
          "color": "white",
          "kind": "pawn",
          "initialKind": "pawn",
          "file": 6,
          "rank": 1,
          "initialFile": 6,
          "initialRank": 1,
          "moved": false,
          "alive": true
        }
      }
    },
    {
      "id": "piece.white.knight.g1",
      "prefab": "prefab.white.knight",
      "transform": {
        "position": [
          2.59,
          0.07,
          3.6260000000000003
        ],
        "scale": [
          10.5,
          10.5,
          10.5
        ]
      },
      "components": {
        "ChessPiece": {
          "color": "white",
          "kind": "knight",
          "initialKind": "knight",
          "file": 6,
          "rank": 0,
          "initialFile": 6,
          "initialRank": 0,
          "moved": false,
          "alive": true
        }
      }
    },
    {
      "id": "piece.white.pawn.h2",
      "prefab": "prefab.white.pawn",
      "transform": {
        "position": [
          3.6260000000000003,
          0.07,
          2.59
        ],
        "scale": [
          10.5,
          10.5,
          10.5
        ]
      },
      "components": {
        "ChessPiece": {
          "color": "white",
          "kind": "pawn",
          "initialKind": "pawn",
          "file": 7,
          "rank": 1,
          "initialFile": 7,
          "initialRank": 1,
          "moved": false,
          "alive": true
        }
      }
    },
    {
      "id": "piece.white.rook.h1",
      "prefab": "prefab.white.rook",
      "transform": {
        "position": [
          3.6260000000000003,
          0.07,
          3.6260000000000003
        ],
        "scale": [
          10.5,
          10.5,
          10.5
        ]
      },
      "components": {
        "ChessPiece": {
          "color": "white",
          "kind": "rook",
          "initialKind": "rook",
          "file": 7,
          "rank": 0,
          "initialFile": 7,
          "initialRank": 0,
          "moved": false,
          "alive": true
        }
      }
    },
    {
      "id": "piece.black.pawn.a7",
      "prefab": "prefab.black.pawn",
      "transform": {
        "position": [
          -3.6260000000000003,
          0.07,
          -2.59
        ],
        "scale": [
          10.5,
          10.5,
          10.5
        ]
      },
      "components": {
        "ChessPiece": {
          "color": "black",
          "kind": "pawn",
          "initialKind": "pawn",
          "file": 0,
          "rank": 6,
          "initialFile": 0,
          "initialRank": 6,
          "moved": false,
          "alive": true
        }
      }
    },
    {
      "id": "piece.black.rook.a8",
      "prefab": "prefab.black.rook",
      "transform": {
        "position": [
          -3.6260000000000003,
          0.07,
          -3.6260000000000003
        ],
        "scale": [
          10.5,
          10.5,
          10.5
        ]
      },
      "components": {
        "ChessPiece": {
          "color": "black",
          "kind": "rook",
          "initialKind": "rook",
          "file": 0,
          "rank": 7,
          "initialFile": 0,
          "initialRank": 7,
          "moved": false,
          "alive": true
        }
      }
    },
    {
      "id": "piece.black.pawn.b7",
      "prefab": "prefab.black.pawn",
      "transform": {
        "position": [
          -2.59,
          0.07,
          -2.59
        ],
        "scale": [
          10.5,
          10.5,
          10.5
        ]
      },
      "components": {
        "ChessPiece": {
          "color": "black",
          "kind": "pawn",
          "initialKind": "pawn",
          "file": 1,
          "rank": 6,
          "initialFile": 1,
          "initialRank": 6,
          "moved": false,
          "alive": true
        }
      }
    },
    {
      "id": "piece.black.knight.b8",
      "prefab": "prefab.black.knight",
      "transform": {
        "position": [
          -2.59,
          0.07,
          -3.6260000000000003
        ],
        "scale": [
          10.5,
          10.5,
          10.5
        ]
      },
      "components": {
        "ChessPiece": {
          "color": "black",
          "kind": "knight",
          "initialKind": "knight",
          "file": 1,
          "rank": 7,
          "initialFile": 1,
          "initialRank": 7,
          "moved": false,
          "alive": true
        }
      }
    },
    {
      "id": "piece.black.pawn.c7",
      "prefab": "prefab.black.pawn",
      "transform": {
        "position": [
          -1.554,
          0.07,
          -2.59
        ],
        "scale": [
          10.5,
          10.5,
          10.5
        ]
      },
      "components": {
        "ChessPiece": {
          "color": "black",
          "kind": "pawn",
          "initialKind": "pawn",
          "file": 2,
          "rank": 6,
          "initialFile": 2,
          "initialRank": 6,
          "moved": false,
          "alive": true
        }
      }
    },
    {
      "id": "piece.black.bishop.c8",
      "prefab": "prefab.black.bishop",
      "transform": {
        "position": [
          -1.554,
          0.07,
          -3.6260000000000003
        ],
        "scale": [
          10.5,
          10.5,
          10.5
        ]
      },
      "components": {
        "ChessPiece": {
          "color": "black",
          "kind": "bishop",
          "initialKind": "bishop",
          "file": 2,
          "rank": 7,
          "initialFile": 2,
          "initialRank": 7,
          "moved": false,
          "alive": true
        }
      }
    },
    {
      "id": "piece.black.pawn.d7",
      "prefab": "prefab.black.pawn",
      "transform": {
        "position": [
          -0.518,
          0.07,
          -2.59
        ],
        "scale": [
          10.5,
          10.5,
          10.5
        ]
      },
      "components": {
        "ChessPiece": {
          "color": "black",
          "kind": "pawn",
          "initialKind": "pawn",
          "file": 3,
          "rank": 6,
          "initialFile": 3,
          "initialRank": 6,
          "moved": false,
          "alive": true
        }
      }
    },
    {
      "id": "piece.black.queen.d8",
      "prefab": "prefab.black.queen",
      "transform": {
        "position": [
          -0.518,
          0.07,
          -3.6260000000000003
        ],
        "scale": [
          10.5,
          10.5,
          10.5
        ]
      },
      "components": {
        "ChessPiece": {
          "color": "black",
          "kind": "queen",
          "initialKind": "queen",
          "file": 3,
          "rank": 7,
          "initialFile": 3,
          "initialRank": 7,
          "moved": false,
          "alive": true
        }
      }
    },
    {
      "id": "piece.black.pawn.e7",
      "prefab": "prefab.black.pawn",
      "transform": {
        "position": [
          0.518,
          0.07,
          -2.59
        ],
        "scale": [
          10.5,
          10.5,
          10.5
        ]
      },
      "components": {
        "ChessPiece": {
          "color": "black",
          "kind": "pawn",
          "initialKind": "pawn",
          "file": 4,
          "rank": 6,
          "initialFile": 4,
          "initialRank": 6,
          "moved": false,
          "alive": true
        }
      }
    },
    {
      "id": "piece.black.king.e8",
      "prefab": "prefab.black.king",
      "transform": {
        "position": [
          0.518,
          0.07,
          -3.6260000000000003
        ],
        "scale": [
          10.5,
          10.5,
          10.5
        ]
      },
      "components": {
        "ChessPiece": {
          "color": "black",
          "kind": "king",
          "initialKind": "king",
          "file": 4,
          "rank": 7,
          "initialFile": 4,
          "initialRank": 7,
          "moved": false,
          "alive": true
        }
      }
    },
    {
      "id": "piece.black.pawn.f7",
      "prefab": "prefab.black.pawn",
      "transform": {
        "position": [
          1.554,
          0.07,
          -2.59
        ],
        "scale": [
          10.5,
          10.5,
          10.5
        ]
      },
      "components": {
        "ChessPiece": {
          "color": "black",
          "kind": "pawn",
          "initialKind": "pawn",
          "file": 5,
          "rank": 6,
          "initialFile": 5,
          "initialRank": 6,
          "moved": false,
          "alive": true
        }
      }
    },
    {
      "id": "piece.black.bishop.f8",
      "prefab": "prefab.black.bishop",
      "transform": {
        "position": [
          1.554,
          0.07,
          -3.6260000000000003
        ],
        "scale": [
          10.5,
          10.5,
          10.5
        ]
      },
      "components": {
        "ChessPiece": {
          "color": "black",
          "kind": "bishop",
          "initialKind": "bishop",
          "file": 5,
          "rank": 7,
          "initialFile": 5,
          "initialRank": 7,
          "moved": false,
          "alive": true
        }
      }
    },
    {
      "id": "piece.black.pawn.g7",
      "prefab": "prefab.black.pawn",
      "transform": {
        "position": [
          2.59,
          0.07,
          -2.59
        ],
        "scale": [
          10.5,
          10.5,
          10.5
        ]
      },
      "components": {
        "ChessPiece": {
          "color": "black",
          "kind": "pawn",
          "initialKind": "pawn",
          "file": 6,
          "rank": 6,
          "initialFile": 6,
          "initialRank": 6,
          "moved": false,
          "alive": true
        }
      }
    },
    {
      "id": "piece.black.knight.g8",
      "prefab": "prefab.black.knight",
      "transform": {
        "position": [
          2.59,
          0.07,
          -3.6260000000000003
        ],
        "scale": [
          10.5,
          10.5,
          10.5
        ]
      },
      "components": {
        "ChessPiece": {
          "color": "black",
          "kind": "knight",
          "initialKind": "knight",
          "file": 6,
          "rank": 7,
          "initialFile": 6,
          "initialRank": 7,
          "moved": false,
          "alive": true
        }
      }
    },
    {
      "id": "piece.black.pawn.h7",
      "prefab": "prefab.black.pawn",
      "transform": {
        "position": [
          3.6260000000000003,
          0.07,
          -2.59
        ],
        "scale": [
          10.5,
          10.5,
          10.5
        ]
      },
      "components": {
        "ChessPiece": {
          "color": "black",
          "kind": "pawn",
          "initialKind": "pawn",
          "file": 7,
          "rank": 6,
          "initialFile": 7,
          "initialRank": 6,
          "moved": false,
          "alive": true
        }
      }
    },
    {
      "id": "piece.black.rook.h8",
      "prefab": "prefab.black.rook",
      "transform": {
        "position": [
          3.6260000000000003,
          0.07,
          -3.6260000000000003
        ],
        "scale": [
          10.5,
          10.5,
          10.5
        ]
      },
      "components": {
        "ChessPiece": {
          "color": "black",
          "kind": "rook",
          "initialKind": "rook",
          "file": 7,
          "rank": 7,
          "initialFile": 7,
          "initialRank": 7,
          "moved": false,
          "alive": true
        }
      }
    },
    {
      "id": "marker.legal.00",
      "prefab": "prefab.marker.legal",
      "transform": {
        "position": [
          0,
          -10,
          0
        ],
        "scale": [
          0.46,
          0.018,
          0.46
        ]
      },
      "components": {
        "LegalMarker": {
          "index": 0
        }
      }
    },
    {
      "id": "marker.legal.01",
      "prefab": "prefab.marker.legal",
      "transform": {
        "position": [
          0,
          -10,
          0
        ],
        "scale": [
          0.46,
          0.018,
          0.46
        ]
      },
      "components": {
        "LegalMarker": {
          "index": 1
        }
      }
    },
    {
      "id": "marker.legal.02",
      "prefab": "prefab.marker.legal",
      "transform": {
        "position": [
          0,
          -10,
          0
        ],
        "scale": [
          0.46,
          0.018,
          0.46
        ]
      },
      "components": {
        "LegalMarker": {
          "index": 2
        }
      }
    },
    {
      "id": "marker.legal.03",
      "prefab": "prefab.marker.legal",
      "transform": {
        "position": [
          0,
          -10,
          0
        ],
        "scale": [
          0.46,
          0.018,
          0.46
        ]
      },
      "components": {
        "LegalMarker": {
          "index": 3
        }
      }
    },
    {
      "id": "marker.legal.04",
      "prefab": "prefab.marker.legal",
      "transform": {
        "position": [
          0,
          -10,
          0
        ],
        "scale": [
          0.46,
          0.018,
          0.46
        ]
      },
      "components": {
        "LegalMarker": {
          "index": 4
        }
      }
    },
    {
      "id": "marker.legal.05",
      "prefab": "prefab.marker.legal",
      "transform": {
        "position": [
          0,
          -10,
          0
        ],
        "scale": [
          0.46,
          0.018,
          0.46
        ]
      },
      "components": {
        "LegalMarker": {
          "index": 5
        }
      }
    },
    {
      "id": "marker.legal.06",
      "prefab": "prefab.marker.legal",
      "transform": {
        "position": [
          0,
          -10,
          0
        ],
        "scale": [
          0.46,
          0.018,
          0.46
        ]
      },
      "components": {
        "LegalMarker": {
          "index": 6
        }
      }
    },
    {
      "id": "marker.legal.07",
      "prefab": "prefab.marker.legal",
      "transform": {
        "position": [
          0,
          -10,
          0
        ],
        "scale": [
          0.46,
          0.018,
          0.46
        ]
      },
      "components": {
        "LegalMarker": {
          "index": 7
        }
      }
    },
    {
      "id": "marker.legal.08",
      "prefab": "prefab.marker.legal",
      "transform": {
        "position": [
          0,
          -10,
          0
        ],
        "scale": [
          0.46,
          0.018,
          0.46
        ]
      },
      "components": {
        "LegalMarker": {
          "index": 8
        }
      }
    },
    {
      "id": "marker.legal.09",
      "prefab": "prefab.marker.legal",
      "transform": {
        "position": [
          0,
          -10,
          0
        ],
        "scale": [
          0.46,
          0.018,
          0.46
        ]
      },
      "components": {
        "LegalMarker": {
          "index": 9
        }
      }
    },
    {
      "id": "marker.legal.10",
      "prefab": "prefab.marker.legal",
      "transform": {
        "position": [
          0,
          -10,
          0
        ],
        "scale": [
          0.46,
          0.018,
          0.46
        ]
      },
      "components": {
        "LegalMarker": {
          "index": 10
        }
      }
    },
    {
      "id": "marker.legal.11",
      "prefab": "prefab.marker.legal",
      "transform": {
        "position": [
          0,
          -10,
          0
        ],
        "scale": [
          0.46,
          0.018,
          0.46
        ]
      },
      "components": {
        "LegalMarker": {
          "index": 11
        }
      }
    },
    {
      "id": "marker.legal.12",
      "prefab": "prefab.marker.legal",
      "transform": {
        "position": [
          0,
          -10,
          0
        ],
        "scale": [
          0.46,
          0.018,
          0.46
        ]
      },
      "components": {
        "LegalMarker": {
          "index": 12
        }
      }
    },
    {
      "id": "marker.legal.13",
      "prefab": "prefab.marker.legal",
      "transform": {
        "position": [
          0,
          -10,
          0
        ],
        "scale": [
          0.46,
          0.018,
          0.46
        ]
      },
      "components": {
        "LegalMarker": {
          "index": 13
        }
      }
    },
    {
      "id": "marker.legal.14",
      "prefab": "prefab.marker.legal",
      "transform": {
        "position": [
          0,
          -10,
          0
        ],
        "scale": [
          0.46,
          0.018,
          0.46
        ]
      },
      "components": {
        "LegalMarker": {
          "index": 14
        }
      }
    },
    {
      "id": "marker.legal.15",
      "prefab": "prefab.marker.legal",
      "transform": {
        "position": [
          0,
          -10,
          0
        ],
        "scale": [
          0.46,
          0.018,
          0.46
        ]
      },
      "components": {
        "LegalMarker": {
          "index": 15
        }
      }
    },
    {
      "id": "marker.legal.16",
      "prefab": "prefab.marker.legal",
      "transform": {
        "position": [
          0,
          -10,
          0
        ],
        "scale": [
          0.46,
          0.018,
          0.46
        ]
      },
      "components": {
        "LegalMarker": {
          "index": 16
        }
      }
    },
    {
      "id": "marker.legal.17",
      "prefab": "prefab.marker.legal",
      "transform": {
        "position": [
          0,
          -10,
          0
        ],
        "scale": [
          0.46,
          0.018,
          0.46
        ]
      },
      "components": {
        "LegalMarker": {
          "index": 17
        }
      }
    },
    {
      "id": "marker.legal.18",
      "prefab": "prefab.marker.legal",
      "transform": {
        "position": [
          0,
          -10,
          0
        ],
        "scale": [
          0.46,
          0.018,
          0.46
        ]
      },
      "components": {
        "LegalMarker": {
          "index": 18
        }
      }
    },
    {
      "id": "marker.legal.19",
      "prefab": "prefab.marker.legal",
      "transform": {
        "position": [
          0,
          -10,
          0
        ],
        "scale": [
          0.46,
          0.018,
          0.46
        ]
      },
      "components": {
        "LegalMarker": {
          "index": 19
        }
      }
    },
    {
      "id": "marker.legal.20",
      "prefab": "prefab.marker.legal",
      "transform": {
        "position": [
          0,
          -10,
          0
        ],
        "scale": [
          0.46,
          0.018,
          0.46
        ]
      },
      "components": {
        "LegalMarker": {
          "index": 20
        }
      }
    },
    {
      "id": "marker.legal.21",
      "prefab": "prefab.marker.legal",
      "transform": {
        "position": [
          0,
          -10,
          0
        ],
        "scale": [
          0.46,
          0.018,
          0.46
        ]
      },
      "components": {
        "LegalMarker": {
          "index": 21
        }
      }
    },
    {
      "id": "marker.legal.22",
      "prefab": "prefab.marker.legal",
      "transform": {
        "position": [
          0,
          -10,
          0
        ],
        "scale": [
          0.46,
          0.018,
          0.46
        ]
      },
      "components": {
        "LegalMarker": {
          "index": 22
        }
      }
    },
    {
      "id": "marker.legal.23",
      "prefab": "prefab.marker.legal",
      "transform": {
        "position": [
          0,
          -10,
          0
        ],
        "scale": [
          0.46,
          0.018,
          0.46
        ]
      },
      "components": {
        "LegalMarker": {
          "index": 23
        }
      }
    },
    {
      "id": "marker.legal.24",
      "prefab": "prefab.marker.legal",
      "transform": {
        "position": [
          0,
          -10,
          0
        ],
        "scale": [
          0.46,
          0.018,
          0.46
        ]
      },
      "components": {
        "LegalMarker": {
          "index": 24
        }
      }
    },
    {
      "id": "marker.legal.25",
      "prefab": "prefab.marker.legal",
      "transform": {
        "position": [
          0,
          -10,
          0
        ],
        "scale": [
          0.46,
          0.018,
          0.46
        ]
      },
      "components": {
        "LegalMarker": {
          "index": 25
        }
      }
    },
    {
      "id": "marker.legal.26",
      "prefab": "prefab.marker.legal",
      "transform": {
        "position": [
          0,
          -10,
          0
        ],
        "scale": [
          0.46,
          0.018,
          0.46
        ]
      },
      "components": {
        "LegalMarker": {
          "index": 26
        }
      }
    },
    {
      "id": "marker.legal.27",
      "prefab": "prefab.marker.legal",
      "transform": {
        "position": [
          0,
          -10,
          0
        ],
        "scale": [
          0.46,
          0.018,
          0.46
        ]
      },
      "components": {
        "LegalMarker": {
          "index": 27
        }
      }
    },
    {
      "id": "marker.arc.00",
      "prefab": "prefab.marker.arc",
      "transform": {
        "position": [
          0,
          -10,
          0
        ],
        "rotation": [
          0,
          0,
          0
        ],
        "scale": [
          0.4,
          0.025,
          0.07
        ]
      },
      "components": {
        "MoveArcMarker": {
          "index": 0
        }
      }
    },
    {
      "id": "marker.arc.01",
      "prefab": "prefab.marker.arc",
      "transform": {
        "position": [
          0,
          -10,
          0
        ],
        "rotation": [
          0,
          0,
          0
        ],
        "scale": [
          0.4,
          0.025,
          0.07
        ]
      },
      "components": {
        "MoveArcMarker": {
          "index": 1
        }
      }
    },
    {
      "id": "marker.arc.02",
      "prefab": "prefab.marker.arc",
      "transform": {
        "position": [
          0,
          -10,
          0
        ],
        "rotation": [
          0,
          0,
          0
        ],
        "scale": [
          0.4,
          0.025,
          0.07
        ]
      },
      "components": {
        "MoveArcMarker": {
          "index": 2
        }
      }
    },
    {
      "id": "marker.arc.03",
      "prefab": "prefab.marker.arc",
      "transform": {
        "position": [
          0,
          -10,
          0
        ],
        "rotation": [
          0,
          0,
          0
        ],
        "scale": [
          0.4,
          0.025,
          0.07
        ]
      },
      "components": {
        "MoveArcMarker": {
          "index": 3
        }
      }
    },
    {
      "id": "marker.arc.04",
      "prefab": "prefab.marker.arc",
      "transform": {
        "position": [
          0,
          -10,
          0
        ],
        "rotation": [
          0,
          0,
          0
        ],
        "scale": [
          0.4,
          0.025,
          0.07
        ]
      },
      "components": {
        "MoveArcMarker": {
          "index": 4
        }
      }
    },
    {
      "id": "marker.arc.05",
      "prefab": "prefab.marker.arc",
      "transform": {
        "position": [
          0,
          -10,
          0
        ],
        "rotation": [
          0,
          0,
          0
        ],
        "scale": [
          0.4,
          0.025,
          0.07
        ]
      },
      "components": {
        "MoveArcMarker": {
          "index": 5
        }
      }
    },
    {
      "id": "marker.selected.edge.00",
      "prefab": "prefab.marker.selected.edge",
      "transform": {
        "position": [
          0,
          -10,
          0
        ],
        "scale": [
          0.46,
          0.025,
          0.025
        ]
      },
      "components": {
        "SelectedEdgeMarker": {
          "index": 0
        }
      }
    },
    {
      "id": "marker.selected.edge.01",
      "prefab": "prefab.marker.selected.edge",
      "transform": {
        "position": [
          0,
          -10,
          0
        ],
        "scale": [
          0.46,
          0.025,
          0.025
        ]
      },
      "components": {
        "SelectedEdgeMarker": {
          "index": 1
        }
      }
    },
    {
      "id": "marker.selected.edge.02",
      "prefab": "prefab.marker.selected.edge",
      "transform": {
        "position": [
          0,
          -10,
          0
        ],
        "scale": [
          0.025,
          0.025,
          0.46
        ]
      },
      "components": {
        "SelectedEdgeMarker": {
          "index": 2
        }
      }
    },
    {
      "id": "marker.selected.edge.03",
      "prefab": "prefab.marker.selected.edge",
      "transform": {
        "position": [
          0,
          -10,
          0
        ],
        "scale": [
          0.025,
          0.025,
          0.46
        ]
      },
      "components": {
        "SelectedEdgeMarker": {
          "index": 3
        }
      }
    },
    {
      "id": "marker.hover",
      "prefab": "prefab.marker.hover",
      "transform": {
        "position": [
          0,
          -10,
          0
        ],
        "scale": [
          0.92,
          0.03,
          0.92
        ]
      },
      "components": {
        "HoverMarker": {}
      }
    },
    {
      "id": "marker.last.from",
      "prefab": "prefab.marker.last",
      "transform": {
        "position": [
          0,
          -10,
          0
        ],
        "scale": [
          0.82,
          0.025,
          0.82
        ]
      },
      "components": {
        "LastMoveMarker": {}
      }
    },
    {
      "id": "marker.last.to",
      "prefab": "prefab.marker.last",
      "transform": {
        "position": [
          0,
          -10,
          0
        ],
        "scale": [
          0.82,
          0.025,
          0.82
        ]
      },
      "components": {
        "LastMoveMarker": {}
      }
    },
    {
      "id": "marker.check",
      "prefab": "prefab.marker.check",
      "transform": {
        "position": [
          0,
          -10,
          0
        ],
        "scale": [
          0.9,
          0.05,
          0.9
        ]
      },
      "components": {
        "CheckMarker": {}
      }
    },
    {
      "id": "table.surface",
      "transform": {
        "position": [
          0,
          -0.34,
          0
        ],
        "rotation": [
          -1.570796,
          0,
          0
        ],
        "scale": [
          22,
          16,
          1
        ]
      },
      "components": {
        "MeshRenderer": {
          "mesh": "mesh.surface",
          "material": "mat.table",
          "receiveShadow": true
        }
      }
    },
    {
      "id": "library.backdrop",
      "transform": {
        "position": [
          0,
          4.5,
          -8.2
        ],
        "scale": [
          30,
          16,
          1
        ]
      },
      "components": {
        "MeshRenderer": {
          "mesh": "mesh.surface",
          "material": "mat.library",
          "castShadow": false,
          "receiveShadow": false
        }
      }
    },
    {
      "id": "board.surface",
      "transform": {
        "position": [
          0,
          0,
          0
        ],
        "rotation": [
          -1.570796,
          0,
          0
        ],
        "scale": [
          9.35,
          9.35,
          1
        ]
      },
      "components": {
        "MeshRenderer": {
          "mesh": "mesh.surface",
          "material": "mat.board",
          "receiveShadow": true
        }
      }
    },
    {
      "id": "board.base",
      "prefab": "prefab.plinth",
      "transform": {
        "position": [
          0,
          -0.23,
          0
        ],
        "scale": [
          9.5,
          0.24,
          9.5
        ]
      }
    },
    {
      "id": "light.ambient",
      "components": {
        "Light": {
          "kind": "ambient",
          "color": "#f2e9de",
          "intensity": 0.4
        }
      }
    },
    {
      "id": "light.key",
      "transform": {
        "position": [
          -5.5,
          9.5,
          6.5
        ],
        "rotation": [
          -0.78,
          -0.42,
          0
        ]
      },
      "components": {
        "Light": {
          "kind": "directional",
          "color": "#fff0dd",
          "intensity": 2.05
        }
      }
    },
    {
      "id": "light.fill",
      "transform": {
        "position": [
          5.5,
          4.5,
          -3.5
        ]
      },
      "components": {
        "Light": {
          "kind": "point",
          "color": "#dce8f3",
          "intensity": 0.52,
          "range": 19
        }
      }
    },
    {
      "id": "camera.main",
      "transform": {
        "position": [
          0.45,
          7.45,
          10.35
        ],
        "rotation": [
          -0.61,
          0.035,
          0
        ]
      },
      "components": {
        "camera": {
          "mode": "perspective",
          "fovY": 37,
          "near": 0.1,
          "far": 50
        }
      }
    }
  ],
  "prefabs": [
    {
      "id": "prefab.plinth",
      "primitive": "box",
      "color": "#2a1309"
    },
    {
      "id": "prefab.marker.legal",
      "primitive": "cylinder",
      "color": "#e0b85b"
    },
    {
      "id": "prefab.marker.hover",
      "primitive": "box",
      "color": "#84c7ff"
    },
    {
      "id": "prefab.marker.selected",
      "primitive": "box",
      "color": "#37df68"
    },
    {
      "id": "prefab.marker.selected.edge",
      "primitive": "box",
      "color": "#37df68"
    },
    {
      "id": "prefab.marker.last",
      "primitive": "cylinder",
      "color": "#8f672f"
    },
    {
      "id": "prefab.marker.check",
      "primitive": "cylinder",
      "color": "#c9484f"
    },
    {
      "id": "prefab.marker.arc",
      "primitive": "box",
      "color": "#f2b94b"
    },
    {
      "color": "#ead8b8",
      "id": "prefab.white.pawn",
      "asset": "assets/models/chess/white-pawn.glb"
    },
    {
      "color": "#ead8b8",
      "id": "prefab.white.rook",
      "asset": "assets/models/chess/white-rook.glb"
    },
    {
      "color": "#ead8b8",
      "id": "prefab.white.knight",
      "asset": "assets/models/chess/white-knight.glb"
    },
    {
      "color": "#ead8b8",
      "id": "prefab.white.bishop",
      "asset": "assets/models/chess/white-bishop.glb"
    },
    {
      "color": "#ead8b8",
      "id": "prefab.white.queen",
      "asset": "assets/models/chess/white-queen.glb"
    },
    {
      "color": "#ead8b8",
      "id": "prefab.white.king",
      "asset": "assets/models/chess/white-king.glb"
    },
    {
      "color": "#100d0a",
      "id": "prefab.black.pawn",
      "asset": "assets/models/chess/black-pawn.glb"
    },
    {
      "color": "#100d0a",
      "id": "prefab.black.rook",
      "asset": "assets/models/chess/black-rook.glb"
    },
    {
      "color": "#100d0a",
      "id": "prefab.black.knight",
      "asset": "assets/models/chess/black-knight.glb"
    },
    {
      "color": "#100d0a",
      "id": "prefab.black.bishop",
      "asset": "assets/models/chess/black-bishop.glb"
    },
    {
      "color": "#100d0a",
      "id": "prefab.black.queen",
      "asset": "assets/models/chess/black-queen.glb"
    },
    {
      "color": "#100d0a",
      "id": "prefab.black.king",
      "asset": "assets/models/chess/black-king.glb"
    }
  ],
  "resources": [
    {
      "id": "ActiveCamera",
      "value": {
        "entity": "camera.main"
      }
    },
    {
      "id": "ChessGame",
      "value": {
        "blackChoiceText": "PLAY BLACK",
        "moveHistoryText": "No moves yet",
        "opponentCapturedText": "—",
        "opponentClockText": "TIME 14:57",
        "opponentNameText": "ARTEMIS",
        "opponentRatingText": "RATING 1592",
        "opponentSideText": "",
        "playerCapturedText": "—",
        "playerClockText": "TIME 14:32",
        "playerNameText": "YOU",
        "playerRatingText": "RATING 1654",
        "playerSideText": "",
        "turnSubText": "MOVE 1",
        "turnText": "READY",
        "statusText": "Choose a side to begin",
        "helpText": "Choose with the buttons or press W / B",
        "moveText": "New game",
        "promotionText": "Promotion: QUEEN",
        "promptText": "WHICH SIDE DO YOU WANT TO PLAY?",
        "whiteChoiceText": "PLAY WHITE"
      }
    }
  ],
  "systems": [
    {
      "id": "chess-game",
      "source": "behavior-metadata",
      "script": {
        "module": "src/scripts/chess.ts",
        "export": "chessGame"
      }
    }
  ],
  "ui": {
    "nodes": [
      {
        "id": "opponent-card",
        "type": "column",
        "layout": {
          "height": 170,
          "inset": {
            "left": 24,
            "top": 34
          },
          "position": "absolute",
          "width": 252
        },
        "style": {
          "backgroundColor": "#090b0de8",
          "borderColor": "#c69a5066",
          "borderRadius": 8,
          "borderWidth": 1,
          "shadow": {
            "blur": 26,
            "color": "#000000a8",
            "offsetY": 12,
            "spread": 0
          }
        }
      },
      {
        "id": "opponent-avatar",
        "type": "text",
        "text": "A",
        "layout": {
          "align": "center",
          "height": 62,
          "inset": {
            "left": 38,
            "top": 49
          },
          "justify": "center",
          "position": "absolute",
          "width": 62
        },
        "style": {
          "backgroundColor": "#1d2d36",
          "borderColor": "#d8a33a99",
          "borderRadius": 5,
          "borderWidth": 1,
          "color": "#dce9ed",
          "fontSize": 38,
          "fontWeight": "bold",
          "textAlign": "center"
        }
      },
      {
        "id": "opponent-name",
        "type": "text",
        "text": "ARTEMIS",
        "layout": {
          "inset": {
            "left": 114,
            "top": 51
          },
          "position": "absolute",
          "width": 148
        },
        "style": {
          "color": "#f1eadf",
          "fontSize": 16,
          "fontWeight": "bold"
        }
      },
      {
        "id": "opponent-side",
        "type": "text",
        "text": "BLACK",
        "layout": {
          "inset": {
            "left": 114,
            "top": 78
          },
          "position": "absolute",
          "width": 148
        },
        "style": {
          "color": "#9d968c",
          "fontSize": 12
        }
      },
      {
        "id": "opponent-rating",
        "type": "text",
        "text": "RATING 1592",
        "layout": {
          "inset": {
            "left": 114,
            "top": 98
          },
          "position": "absolute",
          "width": 148
        },
        "style": {
          "color": "#9d968c",
          "fontSize": 12
        }
      },
      {
        "id": "opponent-clock",
        "type": "text",
        "text": "TIME 14:57",
        "layout": {
          "inset": {
            "left": 38,
            "top": 133
          },
          "position": "absolute",
          "width": 210
        },
        "style": {
          "color": "#e9e0d2",
          "fontSize": 13
        }
      },
      {
        "id": "player-card",
        "type": "column",
        "layout": {
          "height": 132,
          "inset": {
            "bottom": 156,
            "left": 24
          },
          "position": "absolute",
          "width": 252
        },
        "style": {
          "backgroundColor": "#090b0de8",
          "borderColor": "#c69a5066",
          "borderRadius": 8,
          "borderWidth": 1,
          "shadow": {
            "blur": 26,
            "color": "#000000a8",
            "offsetY": 12,
            "spread": 0
          }
        }
      },
      {
        "id": "player-avatar",
        "type": "text",
        "text": "Y",
        "layout": {
          "align": "center",
          "height": 62,
          "inset": {
            "bottom": 168,
            "left": 38
          },
          "justify": "center",
          "position": "absolute",
          "width": 62
        },
        "style": {
          "backgroundColor": "#24282b",
          "borderColor": "#d8a33a99",
          "borderRadius": 5,
          "borderWidth": 1,
          "color": "#dce9ed",
          "fontSize": 38,
          "fontWeight": "bold",
          "textAlign": "center"
        }
      },
      {
        "id": "player-name",
        "type": "text",
        "text": "YOU",
        "layout": {
          "bottom": 234,
          "inset": {
            "left": 114
          },
          "position": "absolute",
          "width": 148
        },
        "style": {
          "color": "#f1eadf",
          "fontSize": 16,
          "fontWeight": "bold"
        }
      },
      {
        "id": "player-side",
        "type": "text",
        "text": "WHITE",
        "layout": {
          "bottom": 211,
          "inset": {
            "left": 114
          },
          "position": "absolute",
          "width": 148
        },
        "style": {
          "color": "#9d968c",
          "fontSize": 12
        }
      },
      {
        "id": "player-rating",
        "type": "text",
        "text": "RATING 1654",
        "layout": {
          "bottom": 191,
          "inset": {
            "left": 114
          },
          "position": "absolute",
          "width": 148
        },
        "style": {
          "color": "#9d968c",
          "fontSize": 12
        }
      },
      {
        "id": "player-clock",
        "type": "text",
        "text": "TIME 14:32",
        "layout": {
          "bottom": 171,
          "inset": {
            "left": 114
          },
          "position": "absolute",
          "width": 148
        },
        "style": {
          "color": "#e9e0d2",
          "fontSize": 13
        }
      },
      {
        "id": "turn-card",
        "type": "column",
        "layout": {
          "height": 96,
          "inset": {
            "right": 24,
            "top": 34
          },
          "position": "absolute",
          "width": 248
        },
        "style": {
          "backgroundColor": "#090b0de8",
          "borderColor": "#c69a5066",
          "borderRadius": 8,
          "borderWidth": 1,
          "shadow": {
            "blur": 26,
            "color": "#000000a8",
            "offsetY": 12,
            "spread": 0
          }
        }
      },
      {
        "id": "turn-dot",
        "type": "text",
        "text": "●",
        "layout": {
          "inset": {
            "right": 220,
            "top": 51
          },
          "position": "absolute",
          "width": 28
        },
        "style": {
          "color": "#7cdb43",
          "fontSize": 26
        }
      },
      {
        "id": "turn",
        "type": "text",
        "text": "YOUR TURN",
        "layout": {
          "inset": {
            "right": 40,
            "top": 51
          },
          "position": "absolute",
          "width": 170
        },
        "style": {
          "color": "#f1eadf",
          "fontSize": 20,
          "fontWeight": "bold"
        }
      },
      {
        "id": "turn-sub",
        "type": "text",
        "text": "MOVE 1",
        "layout": {
          "inset": {
            "right": 40,
            "top": 79
          },
          "position": "absolute",
          "width": 170
        },
        "style": {
          "color": "#9d968c",
          "fontSize": 14
        }
      },
      {
        "id": "move-history-card",
        "type": "column",
        "layout": {
          "height": 300,
          "inset": {
            "right": 24,
            "top": 146
          },
          "position": "absolute",
          "width": 248
        },
        "style": {
          "backgroundColor": "#090b0de8",
          "borderColor": "#c69a5066",
          "borderRadius": 8,
          "borderWidth": 1,
          "shadow": {
            "blur": 26,
            "color": "#000000a8",
            "offsetY": 12,
            "spread": 0
          }
        }
      },
      {
        "id": "move-history-label",
        "type": "text",
        "text": "MOVES",
        "layout": {
          "inset": {
            "right": 40,
            "top": 162
          },
          "position": "absolute",
          "width": 216
        },
        "style": {
          "color": "#9d968c",
          "fontSize": 12
        }
      },
      {
        "id": "move-history",
        "type": "text",
        "text": "No moves yet",
        "layout": {
          "inset": {
            "right": 40,
            "top": 190
          },
          "position": "absolute",
          "width": 216
        },
        "style": {
          "color": "#f1eadf",
          "fontSize": 14,
          "fontWeight": "bold",
          "wrap": "word"
        }
      },
      {
        "id": "status-plate",
        "type": "column",
        "layout": {
          "height": 38,
          "inset": {
            "left": 340,
            "right": 340,
            "top": 18
          },
          "position": "absolute"
        },
        "style": {
          "backgroundColor": "#090b0dcc",
          "borderColor": "#c69a504d",
          "borderRadius": 19,
          "borderWidth": 1,
          "shadow": {
            "blur": 18,
            "color": "#09060499",
            "offsetY": 6,
            "spread": 0
          }
        }
      },
      {
        "id": "status",
        "type": "text",
        "text": "Your move",
        "layout": {
          "align": "center",
          "inset": {
            "left": 360,
            "right": 360,
            "top": 29
          },
          "justify": "center",
          "position": "absolute"
        },
        "style": {
          "color": "#f0d38f",
          "fontSize": 13,
          "fontWeight": "bold",
          "textAlign": "center"
        }
      },
      {
        "id": "promotion",
        "type": "text",
        "text": "Promotion: QUEEN",
        "layout": {
          "bottom": 24,
          "right": 330,
          "position": "absolute",
          "width": 180
        },
        "style": {
          "color": "#9d968c",
          "fontSize": 12
        }
      },
      {
        "id": "help",
        "type": "text",
        "text": "Click piece + destination  |  Drag + drop  |  Arrows + Enter  |  R restart",
        "layout": {
          "align": "center",
          "bottom": 20,
          "inset": {
            "left": 0,
            "right": 0
          },
          "justify": "center",
          "position": "absolute"
        },
        "style": {
          "color": "#9d968c",
          "fontSize": 11,
          "textAlign": "center"
        }
      },
      {
        "id": "new-game",
        "type": "button",
        "action": "restart",
        "label": "NEW GAME",
        "layout": {
          "align": "center",
          "bottom": 84,
          "height": 52,
          "justify": "center",
          "position": "absolute",
          "right": 24,
          "width": 158
        },
        "style": {
          "backgroundColor": "#171816f2",
          "borderColor": "#cda45b70",
          "borderRadius": 8,
          "borderWidth": 1,
          "color": "#f0e9dc",
          "fontSize": 14,
          "fontWeight": "bold",
          "textAlign": "center"
        }
      }
    ],
    "bindings": [
      {
        "node": "opponent-name",
        "resource": "ChessGame.opponentNameText"
      },
      {
        "node": "opponent-side",
        "resource": "ChessGame.opponentSideText"
      },
      {
        "node": "opponent-rating",
        "resource": "ChessGame.opponentRatingText"
      },
      {
        "node": "opponent-clock",
        "resource": "ChessGame.opponentClockText"
      },
      {
        "node": "player-name",
        "resource": "ChessGame.playerNameText"
      },
      {
        "node": "player-side",
        "resource": "ChessGame.playerSideText"
      },
      {
        "node": "player-rating",
        "resource": "ChessGame.playerRatingText"
      },
      {
        "node": "player-clock",
        "resource": "ChessGame.playerClockText"
      },
      {
        "node": "turn",
        "resource": "ChessGame.turnText"
      },
      {
        "node": "turn-sub",
        "resource": "ChessGame.turnSubText"
      },
      {
        "node": "status",
        "resource": "ChessGame.statusText"
      },
      {
        "node": "move-history",
        "resource": "ChessGame.moveHistoryText"
      },
      {
        "node": "promotion",
        "resource": "ChessGame.promotionText"
      },
      {
        "node": "help",
        "resource": "ChessGame.helpText"
      }
    ]
  }
}
